gita_api/__init__.py
gita_api/api/__init__.py
gita_api/api/api_v2/__init__.py
gita_api/api/api_v2/api.py
gita_api/api/api_v2/endpoints/__init__.py
gita_api/api/api_v2/endpoints/gita.py
gita_api/api/deps.py
gita_api/config.py
gita_api/crud.py
gita_api/db/__init__.py
gita_api/db/base_class.py
gita_api/db/init_db.py
gita_api/db/session.py
gita_api/graphql2.py
gita_api/initial_data.py
gita_api/main.py
gita_api/models/__init__.py
gita_api/models/gita.py
gita_api/models/user.py
gita_api/schemas/__init__.py
gita_api/schemas/gita.py
gita_api/utils.py
gita_api-0.0.1.dist-info/LICENSE
gita_api-0.0.1.dist-info/WHEEL
gita_api-0.0.1.dist-info/METADATA
gita_api-0.0.1.dist-info/RECORD
